{"trial_id": "011", "hyperparameters": {"space": [{"class_name": "Float", "config": {"name": "regularizer", "default": 1e-06, "conditions": [], "min_value": 1e-06, "max_value": 0.1, "step": null, "sampling": "log"}}, {"class_name": "Float", "config": {"name": "lr", "default": 1e-06, "conditions": [], "min_value": 1e-06, "max_value": 1.0, "step": null, "sampling": "log"}}, {"class_name": "Int", "config": {"name": "batch_size", "default": null, "conditions": [], "min_value": 1, "max_value": 64, "step": 1, "sampling": "linear"}}], "values": {"regularizer": 0.000503513373436002, "lr": 0.0002784357793629969, "batch_size": 64}}, "metrics": {"metrics": {"loss": {"direction": "min", "observations": [{"value": [0.08343201875686646], "step": 178}]}, "val_loss": {"direction": "min", "observations": [{"value": [0.12766888737678528], "step": 178}]}}}, "score": 0.12766888737678528, "best_step": 178, "status": "COMPLETED", "message": null}