{"trial_id": "0203", "hyperparameters": {"space": [{"class_name": "Int", "config": {"name": "units", "default": null, "conditions": [], "min_value": 32, "max_value": 512, "step": 32, "sampling": "linear"}}, {"class_name": "Float", "config": {"name": "dropout", "default": 0.0, "conditions": [], "min_value": 0.0, "max_value": 0.5, "step": 0.1, "sampling": "linear"}}, {"class_name": "Float", "config": {"name": "learning_rate", "default": 0.0001, "conditions": [], "min_value": 0.0001, "max_value": 0.01, "step": null, "sampling": "log"}}], "values": {"units": 256, "dropout": 0.1, "learning_rate": 0.003827326429344195, "tuner/epochs": 67, "tuner/initial_epoch": 23, "tuner/bracket": 3, "tuner/round": 2, "tuner/trial_id": "0189"}}, "metrics": {"metrics": {"loss": {"direction": "min", "observations": [{"value": [0.04482832923531532], "step": 2}]}, "val_loss": {"direction": "min", "observations": [{"value": [0.0915672555565834], "step": 2}]}}}, "score": 0.0915672555565834, "best_step": 2, "status": "COMPLETED", "message": null}