{"trial_id": "076", "hyperparameters": {"space": [{"class_name": "Float", "config": {"name": "regularizer", "default": 1e-06, "conditions": [], "min_value": 1e-06, "max_value": 0.1, "step": null, "sampling": "log"}}, {"class_name": "Float", "config": {"name": "lr", "default": 1e-06, "conditions": [], "min_value": 1e-06, "max_value": 1.0, "step": null, "sampling": "log"}}, {"class_name": "Int", "config": {"name": "batch_size", "default": null, "conditions": [], "min_value": 1, "max_value": 64, "step": 1, "sampling": "linear"}}], "values": {"regularizer": 1.4574674960914999e-05, "lr": 7.008514320674155e-06, "batch_size": 26}}, "metrics": {"metrics": {"loss": {"direction": "min", "observations": [{"value": [0.9839299321174622], "step": 199}]}, "val_loss": {"direction": "min", "observations": [{"value": [1.3002464771270752], "step": 199}]}}}, "score": 1.3002464771270752, "best_step": 199, "status": "COMPLETED", "message": null}